MANIFEST.in
README.md
setup.py
./variables
markd/__init__.py
markd/main.py
markd.egg-info/PKG-INFO
markd.egg-info/SOURCES.txt
markd.egg-info/dependency_links.txt
markd.egg-info/top_level.txt