Metadata-Version: 2.1
Name: markd
Version: 0.1.18
Summary: A simple python markdown files generator
Home-page: https://github.com/pantsel/markd
Author: Panagis Tselentis
Author-email: tselentispanagis@gmail.com
License: UNKNOWN
Platform: UNKNOWN
Classifier: Operating System :: OS Independent
Classifier: License :: OSI Approved :: GNU General Public License v3 (GPLv3)
Classifier: Programming Language :: Python :: 3
Classifier: Natural Language :: English
Classifier: Topic :: Software Development :: Libraries
Classifier: Environment :: Plugins
